MANIFEST.in
README.md
setup.py
higlass_manage/__init__.py
higlass_manage/browse.py
higlass_manage/cli.py
higlass_manage/common.py
higlass_manage/create.py
higlass_manage/delete.py
higlass_manage/ingest.py
higlass_manage/list.py
higlass_manage/logs.py
higlass_manage/shell.py
higlass_manage/start.py
higlass_manage/stop.py
higlass_manage/update_viewconfs.py
higlass_manage/view.py
higlass_manage.egg-info/PKG-INFO
higlass_manage.egg-info/SOURCES.txt
higlass_manage.egg-info/dependency_links.txt
higlass_manage.egg-info/entry_points.txt
higlass_manage.egg-info/requires.txt
higlass_manage.egg-info/top_level.txt
higlass_manage/redis/redis.conf