Metadata-Version: 1.0
Name: higlass-manage
Version: 0.8.0
Summary: Wrappers for running the HiGlass Docker container
Home-page: https://github.com/pkerpedjiev/higlass-manage
Author: Peter Kerpedjiev
Author-email: pkerpedjiev@gmail.com
License: UNKNOWN
Platform: UNKNOWN
